fast_openai/__init__.py
fast_openai/application.py
fast_openai/client.py
fast_openai/db/__init__.py
fast_openai/db/errors.py
fast_openai/db/objects.py
fast_openai/db/page.py
fast_openai/db/query.py
fast_openai/fields.py
fast_openai/fmt/__init__.py
fast_openai/fmt/jinja.py
fast_openai/fmt/markdownit.py
fast_openai/fmt/pygments.py
fast_openai/json.py
fast_openai/llm/__init__.py
fast_openai/llm/llm.py
fast_openai/llm/schemas.py
fast_openai/odm.py
fast_openai/typedefs.py
fast_openai/utils.py
fast_openai-0.1.5.dist-info/METADATA
fast_openai-0.1.5.dist-info/WHEEL
fast_openai-0.1.5.dist-info/RECORD
