Metadata-Version: 2.1
Name: fast-openai
Version: 0.1.5
Summary: 
Author: Oscar Bahamonde
Author-email: oscar.bahamonde@pucp.pe
Requires-Python: >=3.9,<4.0
Classifier: Programming Language :: Python :: 3
Classifier: Programming Language :: Python :: 3.9
Classifier: Programming Language :: Python :: 3.10
Classifier: Programming Language :: Python :: 3.11
Requires-Dist: aiohttp (>=3.8.5,<4.0.0)
Requires-Dist: fastapi (>=0.68.1,<0.69.0)
Requires-Dist: iso8601 (>=2.0.0,<3.0.0)
Requires-Dist: jinja2 (>=3.1.2,<4.0.0)
Requires-Dist: numpy (>=1.25.2,<2.0.0)
Requires-Dist: openai (>=0.27.8,<0.28.0)
Requires-Dist: python-dotenv (>=1.0.0,<2.0.0)
Requires-Dist: python-multipart (>=0.0.6,<0.0.7)
Requires-Dist: rich (>=13.5.2,<14.0.0)
Requires-Dist: tiktoken (>=0.4.0,<0.5.0)
